python_mpv_zws.py
python_mpv_zws-0.2.2.dist-info/DESCRIPTION.rst
python_mpv_zws-0.2.2.dist-info/METADATA
python_mpv_zws-0.2.2.dist-info/RECORD
python_mpv_zws-0.2.2.dist-info/WHEEL
python_mpv_zws-0.2.2.dist-info/metadata.json
python_mpv_zws-0.2.2.dist-info/top_level.txt
