Metadata-Version: 2.0
Name: python-mpv-zws
Version: 0.2.2
Summary: A python interface to the mpv media player
Home-page: https://github.com/ZWS2014/python-mpv-zws
Author: jaseg, forked by Dan Bright
Author-email: productions@zaziork.com
License: AGPLv2
Platform: UNKNOWN
